typocalypse/__init__.py
typocalypse/__main__.py
typocalypse/typocalypse.py
typocalypse-0.0.1.dist-info/METADATA
typocalypse-0.0.1.dist-info/WHEEL
typocalypse-0.0.1.dist-info/entry_points.txt
typocalypse-0.0.1.dist-info/licenses/LICENSE
typocalypse-0.0.1.dist-info/RECORD
